coronaviruspy/__init__.py
coronaviruspy/cli.py
coronaviruspy-0.3.0.dist-info/entry_points.txt
coronaviruspy-0.3.0.dist-info/WHEEL
coronaviruspy-0.3.0.dist-info/METADATA
coronaviruspy-0.3.0.dist-info/RECORD
